tpds_extension/sha104_105_support/extension.yaml
tpds_extension/sha104_105_support/setup.py
tpds_extension/sha104_105_support/version.py
tpds_extension/sha104_105_support/backend/__init__.py
tpds_extension/sha104_105_support/backend/sha104.yaml
tpds_extension/sha104_105_support/backend/sha105.yaml
tpds_extension/sha104_105_support/backend/sha106.yaml
tpds_extension/sha104_105_support/backend/sha10x_symm_auth_user_inputs.py
tpds_extension/sha104_105_support/backend/api/__init__.py
tpds_extension/sha104_105_support/backend/api/apis.py
tpds_extension/sha104_105_support/backend/api/models.py
tpds_extension/sha104_105_support/backend/api/sha10x.py
tpds_extension/sha104_105_support/backend/api/sha10x_tflxauth.py
tpds_extension/sha104_105_support/backend/api/sha10x_xml_updates.py
tpds_extension/sha104_105_support/backend/api/base/SHA104_base.xml
tpds_extension/sha104_105_support/backend/api/base/SHA105_base.xml
tpds_extension/sha104_105_support/frontend/TrustFlex/Symm Auth Challenge Response.ipynb
tpds_extension/sha104_105_support/frontend/TrustFlex/Symm Auth Diversified Key.ipynb
tpds_extension/sha104_105_support/frontend/TrustFlex/Symm Auth Shared Key.ipynb
tpds_extension/sha104_105_support/frontend/TrustFlex/firmware.zip
tpds_extension/sha104_105_support/frontend/TrustFlex/project_config.h
tpds_extension/sha104_105_support/frontend/TrustFlex/assets/SHA10x_SymmAuth.md
tpds_extension/sha104_105_support/frontend/TrustFlex/assets/SHA10x_SymmAuth_Challenge_Response.md
tpds_extension/sha104_105_support/frontend/TrustFlex/assets/SHA10x_SymmAuth_shared_key.md
tpds_extension/sha104_105_support/frontend/TrustFlex/assets/images/basicsym_td.png
tpds_extension/sha104_105_support/frontend/TrustFlex/assets/images/c_snippet.PNG
tpds_extension/sha104_105_support/frontend/TrustFlex/assets/images/crypto_assets.png
tpds_extension/sha104_105_support/frontend/TrustFlex/assets/images/cryptoassets_shared_key.png
tpds_extension_sha104_105_support-1.2.5.dist-info/METADATA
tpds_extension_sha104_105_support-1.2.5.dist-info/WHEEL
tpds_extension_sha104_105_support-1.2.5.dist-info/top_level.txt
tpds_extension_sha104_105_support-1.2.5.dist-info/RECORD
